pingmeen/__init__.py
pingmeen/pingmeen.py
pingmeen-0.0.8.3.dist-info/LICENSE
pingmeen-0.0.8.3.dist-info/METADATA
pingmeen-0.0.8.3.dist-info/WHEEL
pingmeen-0.0.8.3.dist-info/top_level.txt
pingmeen-0.0.8.3.dist-info/RECORD
