Metadata-Version: 2.1
Name: pingmeen
Version: 0.0.8.3
Summary: Notifications from your Python code
Home-page: UNKNOWN
Author: Nikita M. Minaev
Author-email: nikita.minaev1995@gmail.com
License: UNKNOWN
Platform: UNKNOWN
Classifier: Programming Language :: Python :: 3
Classifier: Operating System :: OS Independent
Requires-Python: >=3.6
